demo_project/__init__.py
demo_project-0.1.0.dist-info/WHEEL
demo_project-0.1.0.dist-info/METADATA
demo_project-0.1.0.dist-info/RECORD
